{
    "instance_name": "Rifki-15",
    "routes": [
        [48, 16, 13, 37, 23],
        [19, 22, 4, 41, 40, 49, 2, 47],
        [6, 17, 26, 12],
        [25, 36, 44, 32, 34, 11, 33],
        [5, 39, 28, 14, 45, 20, 21, 3, 29, 18],
        [27, 31, 8, 24, 7, 50, 46, 9],
        [42, 10, 30],
        [15, 35, 38, 43, 1]
    ],
    "cost": 14613.0,
    "metadata": {
        "source": "kayros 0.2.0.dev0 TD-ACO (seed=1618, time_limit=300.0s)",
        "validated_by": "mamut-routing-lib td Duration checker",
        "route_durations": [1408.0, 2112.0, 789.0, 2658.0, 2748.0, 2347.0, 948.0, 1603.0],
        "route_departure_times": [159.0, 912.9999999999999, 1473.0, 0.0, 1081.0, 720.0, 0.0, 1284.0],
        "authors": "Florian Rascoussier (0nyr)",
        "validated_cost": 14613.0,
        "validated_num_routes": 8,
        "date": "2026-07-06T05:02:46"
    },
    "objective_function": "Duration"
}
